pyi3/__init__.py
pyi3/async_connection.py
pyi3/binding_event.py
pyi3/command_reply.py
pyi3/connection.py
pyi3/container.py
pyi3/meta/__init__.py
pyi3/meta/namedtuple.py
pyi3/mode_event.py
pyi3/output.py
pyi3/protocol.py
pyi3/rect.py
pyi3/sockpath.py
pyi3/version.py
pyi3/window_event.py
pyi3/workspace.py
pyi3/workspace_event.py
pyi3-0.1.1.dist-info/WHEEL
pyi3-0.1.1.dist-info/METADATA
pyi3-0.1.1.dist-info/RECORD
